ecd/__init__.py
ecd/_impl.py
ecd/cli.py
ecd/py.typed
everybody_codes_data-0.4.dist-info/METADATA
everybody_codes_data-0.4.dist-info/WHEEL
everybody_codes_data-0.4.dist-info/entry_points.txt
everybody_codes_data-0.4.dist-info/top_level.txt
everybody_codes_data-0.4.dist-info/RECORD
