Metadata-Version: 2.4
Name: everybody-codes-data
Version: 0.4
Summary: Retrieve and decrypt puzzle input data for everybody.codes events
Author-email: Wim Jeantine-Glenn <hey@wimglenn.com>
License-Expression: MIT
Project-URL: Homepage, https://github.com/wimglenn/everybody-codes-data
Classifier: Intended Audience :: Developers
Classifier: Programming Language :: Python :: 3
Classifier: Topic :: Software Development :: Libraries
Classifier: Topic :: Games/Entertainment :: Puzzle Games
Requires-Python: >=3.10
Requires-Dist: cryptography
Requires-Dist: urllib3
